setup.py
vpopulus_api/__init__.py
vpopulus_api.egg-info/PKG-INFO
vpopulus_api.egg-info/SOURCES.txt
vpopulus_api.egg-info/dependency_links.txt
vpopulus_api.egg-info/not-zip-safe
vpopulus_api.egg-info/requires.txt
vpopulus_api.egg-info/top_level.txt