Metadata-Version: 1.0
Name: vpopulus-api
Version: 0.2.2
Summary: An API for the vPopulus browser game
Home-page: https://github.com/ca1ek/vpopulus_api
Author: ca1ek
Author-email: ca1ekowy@gmail.com
License: MIT
Platform: UNKNOWN
